MT_PY_django_I18n/__init__.py
MT_PY_django_I18n/json_to_po.py
MT_PY_django_I18n/translation.py
MT_PY_django_I18n-0.0.3.dist-info/LICENSE
MT_PY_django_I18n-0.0.3.dist-info/METADATA
MT_PY_django_I18n-0.0.3.dist-info/WHEEL
MT_PY_django_I18n-0.0.3.dist-info/top_level.txt
MT_PY_django_I18n-0.0.3.dist-info/RECORD
