Metadata-Version: 2.1
Name: MT-PY-django-I18n
Version: 0.0.3
Summary: A package to implementing i18n in django
Author-email: Viraj <virajpoojari0905@gmail.com>
Project-URL: Homepage, https://github.com/pypa/sampleproject
Project-URL: Bug Tracker, https://github.com/pypa/sampleproject/issues
Classifier: Programming Language :: Python :: 3
Classifier: License :: OSI Approved :: MIT License
Classifier: Operating System :: OS Independent
Requires-Python: >=3.7
License-File: LICENSE
